scb_tools/__init__.py
scb_tools-0.0.0.dist-info/LICENSE
scb_tools-0.0.0.dist-info/METADATA
scb_tools-0.0.0.dist-info/WHEEL
scb_tools-0.0.0.dist-info/top_level.txt
scb_tools-0.0.0.dist-info/RECORD
